aadhaar/__init__.py
aadhaar/secure_qr/__init__.py
aadhaar/secure_qr/enums.py
aadhaar/secure_qr/exceptions.py
aadhaar/secure_qr/extractor.py
aadhaar/secure_qr/utilities.py
aadhaar_py-2.0.1.dist-info/LICENSE
aadhaar_py-2.0.1.dist-info/WHEEL
aadhaar_py-2.0.1.dist-info/METADATA
aadhaar_py-2.0.1.dist-info/RECORD
