Metadata-Version: 2.1
Name: aadhaar-py
Version: 2.0.1
Summary: Extract embedded information from Aadhaar Secure QR Code.
Home-page: https://github.com/vishaltanwar96/aadhaar-py
License: MIT
Keywords: aadhaar,secure qr code,extractor,qr code,aadhaar secure qr code
Author: Vishal Tanwar
Author-email: vishal.tanwar@outlook.com
Requires-Python: >=3.9,<4.0
Classifier: Development Status :: 5 - Production/Stable
Classifier: Intended Audience :: Developers
Classifier: License :: OSI Approved :: MIT License
Classifier: Operating System :: POSIX :: Linux
Classifier: Programming Language :: Python :: 3
Classifier: Programming Language :: Python :: 3.10
Classifier: Programming Language :: Python :: 3.9
Classifier: Topic :: Software Development :: Libraries
Classifier: Topic :: Software Development :: Libraries :: Python Modules
Classifier: Topic :: Utilities
Classifier: Typing :: Typed
Requires-Dist: Pillow (>=8.4,<10.0)
Requires-Dist: types-Pillow (>=8.3.7,<9.0.0)
Project-URL: Repository, https://github.com/vishaltanwar96/aadhaar-py
